{
  "$schema": "https://developer.microsoft.com/json-schemas/fabric/item/report/definition/page/2.1.0/schema.json",
  "name": "e4a933d17cc64d485e2e",
  "displayName": "Sales",
  "displayOption": "FitToPage",
  "height": 720,
  "width": 1280,
  "objects": {
    "background": [
      {
        "properties": {
          "image": {
            "image": {
              "name": {
                "expr": {
                  "Literal": {
                    "Value": "'Pastel powder tea green plain solid color block swatch blender coordinates.jpg'"
                  }
                }
              },
              "url": {
                "expr": {
                  "ResourcePackageItem": {
                    "PackageName": "RegisteredResources",
                    "PackageType": 1,
                    "ItemName": "Pastel_powder_tea_green_plain_9481760821356077.jpg"
                  }
                }
              },
              "scaling": {
                "expr": {
                  "Literal": {
                    "Value": "'Fill'"
                  }
                }
              }
            }
          },
          "transparency": {
            "expr": {
              "Literal": {
                "Value": "70D"
              }
            }
          }
        }
      }
    ]
  }
}